prometheus_roller/__init__.py
prometheus_roller/roller.py
prometheus_roller/updater.py
prometheus_roller-0.0.2.dist-info/DESCRIPTION.rst
prometheus_roller-0.0.2.dist-info/METADATA
prometheus_roller-0.0.2.dist-info/RECORD
prometheus_roller-0.0.2.dist-info/WHEEL
prometheus_roller-0.0.2.dist-info/metadata.json
prometheus_roller-0.0.2.dist-info/pbr.json
prometheus_roller-0.0.2.dist-info/top_level.txt
