Metadata-Version: 2.0
Name: prometheus-roller
Version: 0.0.2
Summary: Library for aggregating metrics from the Prometheus monitoring system's python client library.
Home-page: https://github.com/turtlemonvh/prometheus_python_roller
Author: Timothy Van Heest
Author-email: timothy@ionic.com
License: MIT
Keywords: prometheus monitoring client metrics
Platform: UNKNOWN
Classifier: Development Status :: 4 - Beta
Classifier: License :: OSI Approved :: MIT License
Classifier: Intended Audience :: Developers
Classifier: Intended Audience :: Information Technology
Classifier: Intended Audience :: System Administrators
Classifier: Topic :: System :: Monitoring
Classifier: Programming Language :: Python :: 2
Classifier: Programming Language :: Python :: 2.6
Classifier: Programming Language :: Python :: 2.7
Classifier: Programming Language :: Python :: 3
Classifier: Programming Language :: Python :: 3.2
Classifier: Programming Language :: Python :: 3.3
Classifier: Programming Language :: Python :: 3.4
Classifier: Programming Language :: Python :: 3.5
Requires-Dist: prometheus-client
